adara_privacy/__init__.py
adara_privacy/identifier.py
adara_privacy/identity.py
adara_privacy/privacy_token.py
adara_privacy/exceptions/__init__.py
adara_privacy/exceptions/instance_not_mutable_error.py
adara_privacy/exceptions/invalid_configuration_format_error.py
adara_privacy/exceptions/missing_environment_variable_error.py
adara_privacy/exceptions/missing_required_setting_error.py
adara_privacy/streamers/__init__.py
adara_privacy/streamers/adara_api_streamer.py
adara_privacy/streamers/file_streamer.py
adara_privacy/streamers/streamer.py
adara_privacy/utils/__init__.py
adara_privacy/utils/config.py
adara_privacy/utils/strings.py
adara_privacy-0.1.5.dist-info/LICENSE
adara_privacy-0.1.5.dist-info/METADATA
adara_privacy-0.1.5.dist-info/WHEEL
adara_privacy-0.1.5.dist-info/top_level.txt
adara_privacy-0.1.5.dist-info/RECORD
