Metadata-Version: 2.1
Name: adara-privacy
Version: 0.1.5
Summary: The Adara Privacy SDK is an open source library which allows you to safely manage sensitive Personally Identifiable Information (PII).
Home-page: https://bitbucket.org/adarainc/adara-privacy-sdk-python
Author: Adara, Inc.
Author-email: privacy-sdk@adara.com
License: UNKNOWN
Platform: UNKNOWN
Classifier: Programming Language :: Python :: 3
Classifier: Operating System :: OS Independent
Requires-Python: >=3.7
Requires-Dist: requests
